adapter/__init__.py
adapter/adapter.py
adapter/cross_validator.py
adapter/utils.py
adapter/estimator/__init__.py
adapter/estimator/base_estimator.py
adapter/estimator/xgboost_classification.py
adapter/estimator/xgboost_regression.py
adapter/optimizer/__init__.py
adapter/optimizer/base_optimizer.py
adapter/optimizer/gp.py
adapter/optimizer/random.py
adapter/supervised_transformer/__init__.py
adapter/supervised_transformer/numerical_target_encoding.py
scikit_optimize_adapter-0.0b1.dist-info/LICENSE
scikit_optimize_adapter-0.0b1.dist-info/METADATA
scikit_optimize_adapter-0.0b1.dist-info/WHEEL
scikit_optimize_adapter-0.0b1.dist-info/top_level.txt
scikit_optimize_adapter-0.0b1.dist-info/RECORD
