Metadata-Version: 2.1
Name: scikit-optimize-adapter
Version: 0.0b1
Summary: Dask parallelized bayesian optimization toolbox
Home-page: UNKNOWN
Author: Jay Kim
License: DSB 3-clause
Platform: UNKNOWN
Requires-Dist: scikit-optimize (>=0.7.4)
Requires-Dist: dask
Requires-Dist: distributed
